README.md
setup.cfg
setup.py
networkqit/__init__.py
networkqit/release.py
networkqit.egg-info/PKG-INFO
networkqit.egg-info/SOURCES.txt
networkqit.egg-info/dependency_links.txt
networkqit.egg-info/requires.txt
networkqit.egg-info/top_level.txt
networkqit/algorithms/__init__.py
networkqit/algorithms/basinhoppingmod.py
networkqit/algorithms/community.py
networkqit/algorithms/optimize.py
networkqit/graphtheory/__init__.py
networkqit/graphtheory/graphs.py
networkqit/graphtheory/matrices.py
networkqit/graphtheory/models/GraphModel.py
networkqit/graphtheory/models/MEModels.py
networkqit/graphtheory/models/Operations.py
networkqit/graphtheory/models/SpatialModels.py
networkqit/graphtheory/models/__init__.py
networkqit/graphtheory/models/compute_mem_models.py
networkqit/graphtheory/models/deprecated.py
networkqit/infotheory/__init__.py
networkqit/infotheory/density.py
networkqit/infotheory/density2.py
networkqit/infotheory/spectral_density.py
networkqit/utils/__init__.py
networkqit/utils/visualization.py