Metadata-Version: 2.1
Name: networkqit
Version: 0.20.0
Summary: A package for fitting spectral entropies of complex networks
Home-page: https://github.com/carlonicolini/networkqit
Author: Carlo Nicolini
Author-email: carlo.nicolini@iit.it
License: UNKNOWN
Keywords: networks complex graph theory entropy physics
Platform: UNKNOWN
Classifier: Development Status :: 4 - Beta
Classifier: Programming Language :: Python :: 3
Classifier: Programming Language :: Python :: 3.5
Classifier: Programming Language :: Python :: 3.6
Provides-Extra: dev
Provides-Extra: test
